{
  "orders": [
    {
      "owner": "GNC",
      "project": "GNC",
      "order_class": "Ecom",
      "owner_reference": "00005008",
      "vendor_reference": "",
      "requested_delivery_date": "",
      "warehouse": "2301",
      "carrier": "GRND",
      "carrier_service": "GRND",
      "addresses": [
        {
          "type": "Shipping",
          "name": "Raquel Jenkins",
          "reference": "",
          "attention_of": "",
          "line_1": "699 Lewelling BLVD",
          "line_2": "",
          "city": "San Leandro",
          "state": "CA",
          "postal_code": "94579",
          "country": "US",
          "lookup": "",
          "phone": "",
          "email": "",
          "fax": "",
          "title": "",
          "greeting": "",
          "first_name": "Raquel",
          "middle_name": "",
          "last_name": "Jenkins",
          "is_residential": false,
          "notes": "",
          "order_id": 1000008008
        },
        {
          "type": "Billing",
          "name": "Raquel Jenkins",
          "reference": "",
          "attention_of": "",
          "line_1": "699 Lewelling BLVD",
          "line_2": "",
          "city": "San Leandro",
          "state": "CA",
          "postal_code": "94579",
          "country": "US",
          "lookup": "",
          "phone": "5104094623",
          "email": "",
          "fax": "",
          "title": "",
          "greeting": "",
          "first_name": "Raquel",
          "middle_name": "",
          "last_name": "Jenkins",
          "is_residential": false,
          "notes": "",
          "order_id": 1000008008
        }
      ],
      "order_lines": [
        {
          "line_number": 1,
          "material": "58033",
          "vendor_lot": "",
          "lot": "",
          "packaging": "",
          "packaged_amount": 1,
          "upc": "",
          "child_lines": [],
          "custom_fields": [],
          "order_id": 1000008008,
          "cost": 0,
          "price": 0
        }
      ],
      "custom_fields": [],
      "shipments": [],
      "lookup": "00005008",
      "instructions": [],
      "currency": "USD",
      "notes": ""
    }
  ]
}